Metadata-Version: 2.1
Name: durc
Version: 3.0.0
Summary: Hierarchical CRUD utils for python projects
Home-page: https://github.com/filipealvesdef/durc
Author: Filipe Alves
Author-email: filipe.alvesdefernando@gmail.com
License: UNKNOWN
Platform: UNKNOWN
